<?xml version="1.0" encoding="utf-8" ?>
<ArrayOfComponent>
  <Component>
    <Level>0</Level>
    <AccessoryList></AccessoryList>
    <CargoFactor>0</CargoFactor>
    <DesignPoints>0</DesignPoints>
    <Load>0</Load>
  </Component>
  <Component>
    <Level>1</Level>
    <AccessoryList>
      <Accessory>Security</Accessory>
    </AccessoryList>
    <CargoFactor>2</CargoFactor>
    <DesignPoints>150</DesignPoints>
    <Load>35</Load>
  </Component>
  <Component>
    <Level>2</Level>
    <AccessoryList>
      <Accessory>Security</Accessory>
    </AccessoryList>
    <CargoFactor>4</CargoFactor>
    <DesignPoints>400</DesignPoints>
    <Load>45</Load>
  </Component>
  <Component>
    <Level>3</Level>
    <AccessoryList>
      <Accessory>Security</Accessory>
    </AccessoryList>
    <CargoFactor>6</CargoFactor>
    <DesignPoints>1000</DesignPoints>
    <Load>60</Load>
  </Component>
  <Component>
    <Level>4</Level>
    <AccessoryList>
      <Accessory>Military</Accessory>
    </AccessoryList>
    <CargoFactor>4</CargoFactor>
    <DesignPoints>2500</DesignPoints>
    <Load>45</Load>
  </Component>
  <Component>
    <Level>5</Level>
    <AccessoryList>
      <Accessory>Military</Accessory>
    </AccessoryList>
    <CargoFactor>6</CargoFactor>
    <DesignPoints>10000</DesignPoints>
    <Load>60</Load>
  </Component>
  <Component>
    <Level>6</Level>
    <AccessoryList>
      <Accessory>Military</Accessory>
    </AccessoryList>
    <CargoFactor>8</CargoFactor>
    <DesignPoints>20000</DesignPoints>
    <Load>110</Load>
  </Component>
</ArrayOfComponent>